medyum/__init__.py
medyum/__main__.py
medyum/medyum.py
medyum/ops.py
medyum-1.0.0.dist-info/LICENSE
medyum-1.0.0.dist-info/METADATA
medyum-1.0.0.dist-info/WHEEL
medyum-1.0.0.dist-info/top_level.txt
medyum-1.0.0.dist-info/RECORD
