Metadata-Version: 2.1
Name: medyum
Version: 1.0.0
Summary: 🧞‍♂️ Stack-oriented programming language in Turkish. Just for fun.
Home-page: UNKNOWN
Author: orhanemree (Orhan Emre Dikicigil)
Author-email: orhanemre.dev@gmail.com
License: MIT
Platform: UNKNOWN
